basic_functions/__init__.py
basic_functions/basic_f.py
basic_functions-0.0.4.dist-info/LICENSE.txt
basic_functions-0.0.4.dist-info/METADATA
basic_functions-0.0.4.dist-info/WHEEL
basic_functions-0.0.4.dist-info/top_level.txt
basic_functions-0.0.4.dist-info/RECORD
