Metadata-Version: 2.1
Name: basic-functions
Version: 0.0.4
Summary: very basic functions for data pre-processing and visualization
Author: Noga Mudrik
Author-email: <nmudrik1@jhmi.edu>
Classifier: Programming Language :: Python :: 3
Classifier: License :: OSI Approved :: MIT License
Classifier: Operating System :: OS Independent
Requires-Python: >=3.8
License-File: LICENSE.txt
Requires-Dist: numpy
Requires-Dist: matplotlib
Requires-Dist: scipy
Requires-Dist: pandas
Requires-Dist: webcolors
Requires-Dist: qpsolvers
Requires-Dist: seaborn
Requires-Dist: colormap
Requires-Dist: sklearn
Requires-Dist: dill
Requires-Dist: mat73
Requires-Dist: easydev
